{
  "status": "ok",
  "message-type": "work",
  "message-version": "1.0.0",
  "message": {
    "institution": [
      {
        "name": "bioRxiv"
      }
    ],
    "indexed": {
      "date-parts": [
        [
          2026,
          1,
          15
        ]
      ],
      "date-time": "2026-01-15T16:46:45Z",
      "timestamp": 1768495605116,
      "version": "3.49.0"
    },
    "posted": {
      "date-parts": [
        [
          2021,
          6,
          22
        ]
      ]
    },
    "group-title": "Scientific Communication and Education",
    "reference-count": 77,
    "publisher": "openRxiv",
    "content-domain": {
      "domain": [],
      "crossmark-restriction": false
    },
    "short-container-title": [],
    "accepted": {
      "date-parts": [
        [
          2021,
          6,
          22
        ]
      ]
    },
    "abstract": "<jats:title>ABSTRACT</jats:title>\n                <jats:sec>\n                  <jats:title>Background</jats:title>\n                  <jats:p>Due to the COVID-19 pandemic, many universities moved to emergency remote teaching (ERT). This allowed institutions to continue their instruction despite not being in person. However, ERT is not without consequences. For example, students may have inadequate technological supports, such as reliable internet and computers. Students may also have poor learning environments at home and may need to find added employment to support their families. Additionally, there were consequences to faculty. It has been shown that female instructors are more disproportionately impacted in terms of mental health issues and increased domestic labor.</jats:p>\n                  <jats:p>\n                    This research aims to investigate instructors\u2019 and students\u2019 perceptions of their transition to ERT. Specifically, we wanted to:\n                    <jats:list list-type=\"order\">\n                      <jats:list-item>\n                        <jats:p>Identify supports and barriers during the transition to ERT</jats:p>\n                      </jats:list-item>\n                      <jats:list-item>\n                        <jats:p>Compare instructors experiences with the student experiences</jats:p>\n                      </jats:list-item>\n                      <jats:list-item>\n                        <jats:p>\n                          Explore these supports and barriers within the context of\n                          <jats:italic>social presence, teaching presence</jats:italic>\n                          , and/or\n                          <jats:italic>cognitive presence</jats:italic>\n                          during ERT as well as how these supports and barriers relate to\n                          <jats:italic>scaffolding</jats:italic>\n                          in emergency remote courses\n                        </jats:p>\n                      </jats:list-item>\n                    </jats:list>\n                  </jats:p>\n                </jats:sec>\n                <jats:sec>\n                  <jats:title>Design</jats:title>\n                  <jats:p>Using grounded theory techniques, we applied two-cycle, qualitative analyses to assess the instructor transcripts. In first-cycle analysis, we used open coding to develop initial ideas from the data. We then used second cycle coding to generate categories with definitions and criteria agreed upon during discussion-based consensus building. Finally, these categories and descriptions were used to code student survey data.</jats:p>\n                </jats:sec>\n                <jats:sec>\n                  <jats:title>Analyses/Interpretations</jats:title>\n                  <jats:p>Instructors identified twice as many barriers as supports in their teaching during the transition to ERT and identified casual and formal conversations with colleagues as valuable supports. Emerging categories for barriers consisted of academic integrity concerns as well as technological difficulties. Similarly, students identified more barriers than supports in their learning during the transition to ERT. More specifically, students described pre-existing course structure, classroom technology, and community as best supporting their learning. Barriers that challenged student learning included classroom environment, student availability, and student emotion and comfort.</jats:p>\n                </jats:sec>\n                <jats:sec>\n                  <jats:title>Contribution</jats:title>\n                  <jats:p>Together, this research will help us understand supports and barriers to teaching and learning during the transition to ERT. This understanding can help us better plan and prepare for future emergencies, particularly at MSIs, where improved communication and increased access to resources for both students and instructors are key.</jats:p>\n                </jats:sec>",
    "DOI": "10.1101/2021.06.21.449058",
    "type": "posted-content",
    "created": {
      "date-parts": [
        [
          2021,
          6,
          22
        ]
      ],
      "date-time": "2021-06-22T15:40:18Z",
      "timestamp": 1624376418000
    },
    "source": "Crossref",
    "is-referenced-by-count": 0,
    "title": [
      "I will teach you here or there, I will try to teach you anywhere: perceived supports and barriers for emergency remote teaching during COVID-19 pandemic"
    ],
    "prefix": "10.64898",
    "author": [
      {
        "ORCID": "https://orcid.org/0000-0002-5590-7502",
        "authenticated-orcid": false,
        "given": "Cristine",
        "family": "Donham",
        "sequence": "first",
        "affiliation": []
      },
      {
        "ORCID": "https://orcid.org/0000-0001-9499-9422",
        "authenticated-orcid": false,
        "given": "Hillary A.",
        "family": "Barron",
        "sequence": "additional",
        "affiliation": []
      },
      {
        "given": "Jourjina",
        "family": "Alkhouri",
        "sequence": "additional",
        "affiliation": []
      },
      {
        "given": "Maya Changaran",
        "family": "Kumarath",
        "sequence": "additional",
        "affiliation": []
      },
      {
        "given": "Wesley",
        "family": "Alejandro",
        "sequence": "additional",
        "affiliation": []
      },
      {
        "ORCID": "https://orcid.org/0000-0002-7819-2167",
        "authenticated-orcid": false,
        "given": "Erik",
        "family": "Menke",
        "sequence": "additional",
        "affiliation": []
      },
      {
        "ORCID": "https://orcid.org/0000-0003-4146-7929",
        "authenticated-orcid": false,
        "given": "Petra",
        "family": "Kranzfelder",
        "sequence": "additional",
        "affiliation": []
      }
    ],
    "member": "54368",
    "reference": [
      {
        "issue": "2",
        "key": "2021062508001278000_2021.06.21.449058v1.1",
        "first-page": "135",
        "article-title": "Designing quality e-learning environments for emergency remote teaching in coronavirus crisis",
        "volume": "11",
        "year": "2020",
        "journal-title": "Interdisciplinary Journal of Virtual Learning in Medical Sciences"
      },
      {
        "key": "2021062508001278000_2021.06.21.449058v1.2",
        "first-page": "15",
        "article-title": "Foundations of educational theory for online learning",
        "volume": "2",
        "year": "2004",
        "journal-title": "Theory and practice of online learning"
      },
      {
        "key": "2021062508001278000_2021.06.21.449058v1.3",
        "unstructured": "Anderson, T. , Liam, R. , Garrison, D. R. , & Archer, W. (2001a). Assessing teaching presence in a computer conferencing context."
      },
      {
        "key": "2021062508001278000_2021.06.21.449058v1.4",
        "doi-asserted-by": "crossref",
        "unstructured": "Anderson, T. , Liam, R. , Garrison, D. R. , & Archer, W. (2001b). Assessing teaching presence in a computer conferencing context. Journal of Asynchronous Learning Networks, 5(2).",
        "DOI": "10.24059/olj.v5i2.1875"
      },
      {
        "key": "2021062508001278000_2021.06.21.449058v1.5",
        "doi-asserted-by": "publisher",
        "DOI": "10.1016/j.iheduc.2008.06.003"
      },
      {
        "key": "2021062508001278000_2021.06.21.449058v1.6",
        "unstructured": "Bender, T. (2012). Discussion-based online teaching to enhance student learning: Theory, practice and assessment. Stylus Publishing, LLC."
      },
      {
        "key": "2021062508001278000_2021.06.21.449058v1.7",
        "unstructured": "Berk, L. E. (2003). Child development 6th ed. Pearson."
      },
      {
        "issue": "1",
        "key": "2021062508001278000_2021.06.21.449058v1.8",
        "first-page": "i",
        "article-title": "Emergency remote teaching in a time of global crisis due to CoronaVirus pandemic",
        "volume": "15",
        "year": "2020",
        "journal-title": "Asian Journal of Distance Education"
      },
      {
        "key": "2021062508001278000_2021.06.21.449058v1.9",
        "doi-asserted-by": "crossref",
        "unstructured": "Branch, R. M. , & Kopcha, T. J. (2014). Instructional design models. In Handbook of research on educational communications and technology (pp. 77\u201387). Springer.",
        "DOI": "10.1007/978-1-4614-3185-5_7"
      },
      {
        "key": "2021062508001278000_2021.06.21.449058v1.10",
        "unstructured": "Brooks, C. , & Grajek, S. (2020). Faculty readiness to begin fully remote teaching. Educause review."
      },
      {
        "key": "2021062508001278000_2021.06.21.449058v1.11",
        "unstructured": "Burke, N. J. , I. Yen , and T. Hurd . (2020). COVID-19 reveals gaps in the Valley\u2019s public health system, but improvement is possible. Merced Sun-Star."
      },
      {
        "issue": "4",
        "key": "2021062508001278000_2021.06.21.449058v1.12",
        "doi-asserted-by": "crossref",
        "first-page": "557",
        "DOI": "10.1007/s11528-020-00491-7",
        "article-title": "20 Years of the Community of Inquiry Framework",
        "volume": "64",
        "year": "2020",
        "journal-title": "TechTrends"
      },
      {
        "key": "2021062508001278000_2021.06.21.449058v1.13",
        "unstructured": "Charmaz, K. (2006). Constructing grounded theory: A practical guide through qualitative analysis. sage."
      },
      {
        "key": "2021062508001278000_2021.06.21.449058v1.14",
        "unstructured": "Chavez, N. (2020). The coronavirus pandemic could shut down schools for months, leaving some students hungry and far behind their peers. CNN."
      },
      {
        "key": "2021062508001278000_2021.06.21.449058v1.15",
        "unstructured": "Commission, F. C. (2018). Broadband deployment report. Washington, DC: Retrieved from https://www.fcc.gov [Google Scholar]."
      },
      {
        "issue": "1",
        "key": "2021062508001278000_2021.06.21.449058v1.16",
        "doi-asserted-by": "crossref",
        "first-page": "134",
        "DOI": "10.1016/j.jaac.2020.08.466",
        "article-title": "Impact of COVID-19 Pandemic on College Student Mental Health and Wellness",
        "volume": "60",
        "year": "2021",
        "journal-title": "Journal of the American Academy of Child & Adolescent Psychiatry"
      },
      {
        "key": "2021062508001278000_2021.06.21.449058v1.17",
        "unstructured": "Corbin, J. , & Strauss, A. (2014). Basics of qualitative research: Techniques and procedures for developing grounded theory. Sage publications."
      },
      {
        "key": "2021062508001278000_2021.06.21.449058v1.18",
        "doi-asserted-by": "publisher",
        "DOI": "10.1007/BF00988593"
      },
      {
        "key": "2021062508001278000_2021.06.21.449058v1.19",
        "unstructured": "Council, N. R. (2012). Discipline-based education research: Understanding and improving learning in undergraduate science and engineering. National Academies Press."
      },
      {
        "issue": "3",
        "key": "2021062508001278000_2021.06.21.449058v1.20",
        "doi-asserted-by": "crossref",
        "first-page": "222",
        "DOI": "10.1080/10899995.2019.1580179",
        "article-title": "Social presence enhances student performance in an online geology course but depends on instructor facilitation",
        "volume": "67",
        "year": "2019",
        "journal-title": "Journal of Geoscience Education"
      },
      {
        "issue": "2",
        "key": "2021062508001278000_2021.06.21.449058v1.21",
        "first-page": "156",
        "article-title": "Deciding between traditional and online formats: Exploring the role of learning advantages, flexibility, and compensatory adaptation",
        "volume": "12",
        "year": "2011",
        "journal-title": "Journal of Behavioral and Applied Management"
      },
      {
        "key": "2021062508001278000_2021.06.21.449058v1.22",
        "doi-asserted-by": "crossref",
        "unstructured": "Dewey, J. (1986). Experience and education. The Educational Forum,",
        "DOI": "10.1080/00131728609335764"
      },
      {
        "key": "2021062508001278000_2021.06.21.449058v1.23",
        "unstructured": "Donner, F. (2020). How women are getting squeezed by the pandemic. The New York Times."
      },
      {
        "key": "2021062508001278000_2021.06.21.449058v1.24",
        "unstructured": "Duchesne, S. , & McMaugh, A. (2018). Educational psychology for learning and teaching. Cengage AU."
      },
      {
        "key": "2021062508001278000_2021.06.21.449058v1.25",
        "unstructured": "Erickson, M. , & Wattiaux, M. A. (2021). Instructor and student responses to COVID 19 emergency remote learning: A preliminary investigation of ten undergraduate animal sciences courses. Natural Sciences Education, e20039."
      },
      {
        "key": "2021062508001278000_2021.06.21.449058v1.26",
        "doi-asserted-by": "crossref",
        "unstructured": "Garrison, D. R. (2016). E-learning in the 21st century: A community of inquiry framework for research and practice. Taylor & Francis.",
        "DOI": "10.4324/9781315667263"
      },
      {
        "key": "2021062508001278000_2021.06.21.449058v1.27",
        "doi-asserted-by": "publisher",
        "DOI": "10.1016/S1096-7516(00)00016-6"
      },
      {
        "key": "2021062508001278000_2021.06.21.449058v1.28",
        "doi-asserted-by": "publisher",
        "DOI": "10.1016/S1096-7516(00)00016-6"
      },
      {
        "key": "2021062508001278000_2021.06.21.449058v1.29",
        "doi-asserted-by": "publisher",
        "DOI": "10.1016/j.iheduc.2009.10.003"
      },
      {
        "key": "2021062508001278000_2021.06.21.449058v1.30",
        "doi-asserted-by": "publisher",
        "DOI": "10.1016/j.iheduc.2007.04.001"
      },
      {
        "key": "2021062508001278000_2021.06.21.449058v1.31",
        "doi-asserted-by": "publisher",
        "DOI": "10.1207/s15389286ajde1903_2"
      },
      {
        "key": "2021062508001278000_2021.06.21.449058v1.32",
        "doi-asserted-by": "publisher",
        "DOI": "10.1016/j.iheduc.2009.10.002"
      },
      {
        "issue": "11",
        "key": "2021062508001278000_2021.06.21.449058v1.33",
        "doi-asserted-by": "crossref",
        "first-page": "304",
        "DOI": "10.3390/educsci10110304",
        "article-title": "Compassionate flexibility and self-discipline: Student adaptation to emergency remote teaching in an integrated engineering energy course during COVID-19",
        "volume": "10",
        "year": "2020",
        "journal-title": "Education Sciences"
      },
      {
        "key": "2021062508001278000_2021.06.21.449058v1.34",
        "unstructured": "Hammond, J. (2001). Scaffolding: Teaching and learning in language and literacy education. ERIC."
      },
      {
        "key": "2021062508001278000_2021.06.21.449058v1.35",
        "first-page": "8",
        "article-title": "What is scaffolding",
        "volume": "8",
        "year": "2005",
        "journal-title": "Teachers\u2019 voices"
      },
      {
        "key": "2021062508001278000_2021.06.21.449058v1.36",
        "first-page": "1",
        "article-title": "The difference between emergency remote teaching and online learning",
        "volume": "27",
        "year": "2020",
        "journal-title": "Educause review"
      },
      {
        "key": "2021062508001278000_2021.06.21.449058v1.37",
        "doi-asserted-by": "publisher",
        "DOI": "10.1111/j.1540-4609.2006.00099.x"
      },
      {
        "key": "2021062508001278000_2021.06.21.449058v1.38",
        "doi-asserted-by": "crossref",
        "first-page": "106713",
        "DOI": "10.1016/j.chb.2021.106713",
        "article-title": "Emergency remote teaching and students\u2019 academic performance in higher education during the COVID-19 pandemic: A case study",
        "volume": "119",
        "year": "2021",
        "journal-title": "Computers in Human Behavior"
      },
      {
        "issue": "2",
        "key": "2021062508001278000_2021.06.21.449058v1.39",
        "doi-asserted-by": "crossref",
        "first-page": "125",
        "DOI": "10.1023/A:1012581113983",
        "article-title": "Providing the scaffold: A model for early childhood/primary teacher preparation",
        "volume": "29",
        "year": "2001",
        "journal-title": "Early Childhood Education Journal"
      },
      {
        "issue": "2",
        "key": "2021062508001278000_2021.06.21.449058v1.40",
        "first-page": "6",
        "article-title": "US Faculty and Administrators\u2019 Experiences and Approaches in the Early Weeks of the COVID-19 Pandemic",
        "volume": "24",
        "year": "2020",
        "journal-title": "Online Learning"
      },
      {
        "issue": "2",
        "key": "2021062508001278000_2021.06.21.449058v1.41",
        "doi-asserted-by": "crossref",
        "first-page": "020106",
        "DOI": "10.1103/PhysRevPhysEducRes.16.020106",
        "article-title": "Demographics of physics education research",
        "volume": "16",
        "year": "2020",
        "journal-title": "Physical Review Physics Education Research"
      },
      {
        "issue": "1",
        "key": "2021062508001278000_2021.06.21.449058v1.42",
        "doi-asserted-by": "crossref",
        "first-page": "295",
        "DOI": "10.1007/s11423-020-09884-0",
        "article-title": "Design considerations in emergency remote teaching during the COVID-19 pandemic: A human-centered approach",
        "volume": "69",
        "year": "2021",
        "journal-title": "Educational Technology Research and Development"
      },
      {
        "issue": "9",
        "key": "2021062508001278000_2021.06.21.449058v1.43",
        "doi-asserted-by": "crossref",
        "first-page": "e0239696",
        "DOI": "10.1371/journal.pone.0239696",
        "article-title": "The impact of the COVID-19 epidemic on mental health of undergraduate students in New Jersey, cross-sectional study",
        "volume": "15",
        "year": "2020",
        "journal-title": "PLoS One"
      },
      {
        "key": "2021062508001278000_2021.06.21.449058v1.44",
        "unstructured": "[Record #259 is using a reference type undefined in this output style.]"
      },
      {
        "issue": "2",
        "key": "2021062508001278000_2021.06.21.449058v1.45",
        "first-page": "196",
        "article-title": "A Structural Equation Model of Predictors of Online Learners\u2019 Engagement and Satisfaction",
        "volume": "23",
        "year": "2019",
        "journal-title": "Online Learning"
      },
      {
        "issue": "2",
        "key": "2021062508001278000_2021.06.21.449058v1.46",
        "doi-asserted-by": "crossref",
        "first-page": "83",
        "DOI": "10.1007/s10755-006-9010-z",
        "article-title": "Implementing effective online teaching practices: Voices of exemplary faculty",
        "volume": "31",
        "year": "2006",
        "journal-title": "Innovative Higher Education"
      },
      {
        "issue": "1",
        "key": "2021062508001278000_2021.06.21.449058v1.47",
        "doi-asserted-by": "crossref",
        "first-page": "3",
        "DOI": "10.1186/s41039-019-0098-z",
        "article-title": "Using reflections and questioning to engage and challenge online graduate learners in education",
        "volume": "14",
        "year": "2019",
        "journal-title": "Research and Practice in Technology Enhanced Learning"
      },
      {
        "issue": "2",
        "key": "2021062508001278000_2021.06.21.449058v1.48",
        "first-page": "5",
        "article-title": "The Sloan semester",
        "volume": "12",
        "year": "2008",
        "journal-title": "Journal of Asynchronous Learning Networks"
      },
      {
        "key": "2021062508001278000_2021.06.21.449058v1.49",
        "doi-asserted-by": "crossref",
        "first-page": "21",
        "DOI": "10.1016/j.iheduc.2017.06.002",
        "article-title": "Investigating student engagement in blended learning settings using experience sampling and structural equation modeling",
        "volume": "35",
        "year": "2017",
        "journal-title": "The Internet and Higher Education"
      },
      {
        "key": "2021062508001278000_2021.06.21.449058v1.50",
        "unstructured": "Miles, M. B. , Huberman, A. M. , & Salda\u00f1a, J. (2018). Qualitative data analysis: A methods sourcebook. Sage publications."
      },
      {
        "issue": "2-3",
        "key": "2021062508001278000_2021.06.21.449058v1.51",
        "doi-asserted-by": "crossref",
        "first-page": "83",
        "DOI": "10.3233/ISU-2000-202-304",
        "article-title": "Evaluating online teaching and learning",
        "volume": "20",
        "year": "2000",
        "journal-title": "Information Services & Use"
      },
      {
        "key": "2021062508001278000_2021.06.21.449058v1.52",
        "doi-asserted-by": "publisher",
        "DOI": "10.1080/0158791990200205"
      },
      {
        "issue": "1",
        "key": "2021062508001278000_2021.06.21.449058v1.53",
        "doi-asserted-by": "crossref",
        "first-page": "42",
        "DOI": "10.4018/IJOPCD.2018010104",
        "article-title": "Adapting the TPACK framework for online teaching within higher education",
        "volume": "8",
        "year": "2018",
        "journal-title": "International Journal of Online Pedagogy and Course Design (IJOPCD)"
      },
      {
        "key": "2021062508001278000_2021.06.21.449058v1.54",
        "unstructured": "Piaget, J. (1976). To Understand is to Invent: The Future of Education. Penguin Books. https://books.google.com/books?id=OE8sAAAAYAAJ"
      },
      {
        "issue": "4",
        "key": "2021062508001278000_2021.06.21.449058v1.55",
        "doi-asserted-by": "crossref",
        "first-page": "ar60",
        "DOI": "10.1187/cbe.20-06-0126",
        "article-title": "A Pandemic Crash Course: Learning to Teach Equitably in Synchronous Online Classes",
        "volume": "19",
        "year": "2020",
        "journal-title": "CBE\u2014Life Sciences Education"
      },
      {
        "key": "2021062508001278000_2021.06.21.449058v1.56",
        "doi-asserted-by": "crossref",
        "first-page": "402",
        "DOI": "10.1016/j.chb.2017.02.001",
        "article-title": "Social presence in relation to students\u2019 satisfaction and learning in the online environment: A meta-analysis",
        "volume": "71",
        "year": "2017",
        "journal-title": "Computers in Human Behavior"
      },
      {
        "issue": "2",
        "key": "2021062508001278000_2021.06.21.449058v1.57",
        "first-page": "473",
        "article-title": "Supporting the mental health of preservice teachers in COVID-19 through trauma-informed educational practices and adaptive formative assessment tools",
        "volume": "28",
        "year": "2020",
        "journal-title": "Journal of Technology and Teacher Education"
      },
      {
        "key": "2021062508001278000_2021.06.21.449058v1.58",
        "unstructured": "Schwartzman, R. (2020). Pandemic Pedagogy Facebook Group"
      },
      {
        "issue": "1",
        "key": "2021062508001278000_2021.06.21.449058v1.59",
        "first-page": "ev22i21.2405",
        "article-title": "Resilient Instructional Strategies: Helping Students Cope and Thrive in Crisis",
        "volume": "22",
        "year": "2021",
        "journal-title": "Journal of microbiology & biology education"
      },
      {
        "key": "2021062508001278000_2021.06.21.449058v1.60",
        "doi-asserted-by": "publisher",
        "DOI": "10.2190/EC.39.4.b"
      },
      {
        "issue": "3",
        "key": "2021062508001278000_2021.06.21.449058v1.61",
        "doi-asserted-by": "crossref",
        "first-page": "157",
        "DOI": "10.1097/01.NEP.0000000000000130",
        "article-title": "Developing an instrument for evidence-based peer review of faculty online teaching",
        "volume": "38",
        "year": "2017",
        "journal-title": "Nursing Education Perspectives"
      },
      {
        "issue": "2",
        "key": "2021062508001278000_2021.06.21.449058v1.62",
        "doi-asserted-by": "crossref",
        "first-page": "139",
        "DOI": "10.15173/ijsap.v3i2.3683",
        "article-title": "Exploring the Impact of the Students Assessing Teaching and Learning Program",
        "volume": "3",
        "year": "2019",
        "journal-title": "International Journal for Students as Partners"
      },
      {
        "issue": "3",
        "key": "2021062508001278000_2021.06.21.449058v1.63",
        "doi-asserted-by": "crossref",
        "first-page": "378",
        "DOI": "10.1111/jcal.12340",
        "article-title": "Students\u2019 engagement characteristics predict success and completion of online courses",
        "volume": "35",
        "year": "2019",
        "journal-title": "Journal of Computer Assisted Learning"
      },
      {
        "key": "2021062508001278000_2021.06.21.449058v1.64",
        "unstructured": "Stake, R. E. (2005). Qualitative case studies."
      },
      {
        "key": "2021062508001278000_2021.06.21.449058v1.65",
        "doi-asserted-by": "publisher",
        "DOI": "10.1177/002221949803100404"
      },
      {
        "key": "2021062508001278000_2021.06.21.449058v1.66",
        "unstructured": "Strauss, A. , & Corbin, J. (1998). Basics of qualitative research techniques. Citeseer."
      },
      {
        "key": "2021062508001278000_2021.06.21.449058v1.67",
        "unstructured": "University of California, U. (2020a). Fall 2020 Student Enrollment. https://www.universityofcalifornia.edu/infocenter/fall-enrollment-glance"
      },
      {
        "key": "2021062508001278000_2021.06.21.449058v1.68",
        "unstructured": "University of California, U. (2020b). Fall 2020 workforce diversity. https://www.universityofcalifornia.edu/infocenter/uc-workforce-diversity"
      },
      {
        "key": "2021062508001278000_2021.06.21.449058v1.69",
        "unstructured": "Vygotsky, L. S. (1978). Mind in society: the development of higher psychological processes. Harvard University Press. https://books.google.com/books?id=SDiAuAEACAAJ"
      },
      {
        "key": "2021062508001278000_2021.06.21.449058v1.70",
        "doi-asserted-by": "crossref",
        "unstructured": "Vygotsky, L. S. (1980). Mind in society: The development of higher psychological processes. Harvard university press.",
        "DOI": "10.2307/j.ctvjf9vz4"
      },
      {
        "issue": "4",
        "key": "2021062508001278000_2021.06.21.449058v1.71",
        "doi-asserted-by": "crossref",
        "first-page": "411",
        "DOI": "10.1080/14703290802377307",
        "article-title": "A generic model for guiding the integration of ICT into teaching and learning",
        "volume": "45",
        "year": "2008",
        "journal-title": "Innovations in education and teaching international"
      },
      {
        "key": "2021062508001278000_2021.06.21.449058v1.72",
        "doi-asserted-by": "publisher",
        "DOI": "10.1080/07294360.2010.489237"
      },
      {
        "key": "2021062508001278000_2021.06.21.449058v1.73",
        "doi-asserted-by": "crossref",
        "unstructured": "Wells, G. (1999). Dialogic inquiry: Towards a socio-cultural practice and theory of education. Cambridge University Press.",
        "DOI": "10.1017/CBO9780511605895"
      },
      {
        "issue": "2",
        "key": "2021062508001278000_2021.06.21.449058v1.74",
        "first-page": "189",
        "article-title": "Should teachers be trained in emergency remote teaching? Lessons learned from the COVID-19 pandemic",
        "volume": "28",
        "year": "2020",
        "journal-title": "Journal of Technology and Teacher Education"
      },
      {
        "key": "2021062508001278000_2021.06.21.449058v1.75",
        "doi-asserted-by": "crossref",
        "unstructured": "Whittle, C. , Tiwari, S. , Yan, S. , & Williams, J. (2020). Emergency remote teaching environment: a conceptual framework for responsive online teaching in crises. Information and Learning Sciences.",
        "DOI": "10.1108/ILS-04-2020-0099"
      },
      {
        "key": "2021062508001278000_2021.06.21.449058v1.76",
        "doi-asserted-by": "publisher",
        "DOI": "10.1111/j.1469-7610.1976.tb00381.x"
      },
      {
        "key": "2021062508001278000_2021.06.21.449058v1.77",
        "doi-asserted-by": "publisher",
        "DOI": "10.1207/s15389286ajde2002_2"
      }
    ],
    "container-title": [],
    "original-title": [],
    "link": [
      {
        "URL": "https://syndication.highwire.org/content/doi/10.1101/2021.06.21.449058",
        "content-type": "unspecified",
        "content-version": "vor",
        "intended-application": "similarity-checking"
      }
    ],
    "deposited": {
      "date-parts": [
        [
          2026,
          1,
          15
        ]
      ],
      "date-time": "2026-01-15T01:51:50Z",
      "timestamp": 1768441910000
    },
    "score": 1,
    "resource": {
      "primary": {
        "URL": "http://biorxiv.org/lookup/doi/10.1101/2021.06.21.449058"
      }
    },
    "subtitle": [],
    "short-title": [],
    "issued": {
      "date-parts": [
        [
          2021,
          6,
          22
        ]
      ]
    },
    "references-count": 77,
    "URL": "https://doi.org/10.1101/2021.06.21.449058",
    "relation": {
      "is-preprint-of": [
        {
          "id-type": "doi",
          "id": "10.1186/s40594-022-00335-1",
          "asserted-by": "subject"
        }
      ]
    },
    "subject": [],
    "published": {
      "date-parts": [
        [
          2021,
          6,
          22
        ]
      ]
    },
    "subtype": "preprint"
  }
}