{
  "status": "ok",
  "message-type": "work",
  "message-version": "1.0.0",
  "message": {
    "institution": [
      {
        "name": "medRxiv"
      }
    ],
    "indexed": {
      "date-parts": [
        [
          2026,
          1,
          16
        ]
      ],
      "date-time": "2026-01-16T09:28:44Z",
      "timestamp": 1768555724187,
      "version": "3.49.0"
    },
    "posted": {
      "date-parts": [
        [
          2021,
          11,
          11
        ]
      ]
    },
    "group-title": "Oncology",
    "reference-count": 18,
    "publisher": "openRxiv",
    "content-domain": {
      "domain": [],
      "crossmark-restriction": false
    },
    "short-container-title": [],
    "accepted": {
      "date-parts": [
        [
          2021,
          11,
          11
        ]
      ]
    },
    "abstract": "<jats:title>Summary</jats:title>\n                <jats:p>Patients with cancer are more likely to have impaired immune responses to SARS CoV-2 vaccines. We studied the breadth of responses against SARS CoV-2 variants followingly primary vaccination in 178 patients with a variety of tumor types, and after booster doses in a subset. Neutralization of alpha, beta, gamma and delta SARS-CoV-2 variants was impaired relative to wildtype (Wuhan), regardless of vaccine type. Regardless of viral variant, mRNA1273 was the most immunogenic, followed by BNT162b2 and then Ad26.COV2.S. Neutralization of more variants (breadth) was associated with higher magnitude of wildtype neutralization, and increase with time since vaccination; increased age associated with lower breadth. Anti-spike binding antibody concentrations were a good surrogate for breadth (PPV=90% at &gt;1000U/ml). Booster SARS-CoV-2 vaccines conferred enhanced breadth. These data suggest that achieving a high antibody titer is desirable to achieve broad neutralization; a single booster dose with current vaccines increases breadth of responses against variants.</jats:p>",
    "DOI": "10.1101/2021.11.10.21265988",
    "type": "posted-content",
    "created": {
      "date-parts": [
        [
          2021,
          11,
          11
        ]
      ],
      "date-time": "2021-11-11T13:55:17Z",
      "timestamp": 1636638917000
    },
    "source": "Crossref",
    "is-referenced-by-count": 3,
    "title": [
      "Neutralization breadth of SARS CoV-2 viral variants following primary series and booster SARS CoV-2 vaccines in patients with cancer"
    ],
    "prefix": "10.64898",
    "author": [
      {
        "ORCID": "https://orcid.org/0000-0003-4281-8882",
        "authenticated-orcid": false,
        "given": "Vivek",
        "family": "Naranbhai",
        "sequence": "first",
        "affiliation": []
      },
      {
        "given": "Kerri J St.",
        "family": "Denis",
        "sequence": "additional",
        "affiliation": []
      },
      {
        "given": "Evan C",
        "family": "Lam",
        "sequence": "additional",
        "affiliation": []
      },
      {
        "given": "Onosereme",
        "family": "Ofoman",
        "sequence": "additional",
        "affiliation": []
      },
      {
        "given": "Wilfredo-Garcia",
        "family": "Beltran",
        "sequence": "additional",
        "affiliation": []
      },
      {
        "given": "Cristhian",
        "family": "Berrios",
        "sequence": "additional",
        "affiliation": []
      },
      {
        "given": "Atul K.",
        "family": "Bhan",
        "sequence": "additional",
        "affiliation": []
      },
      {
        "given": "Justin F.",
        "family": "Gainor",
        "sequence": "additional",
        "affiliation": []
      },
      {
        "given": "Alejandro B.",
        "family": "Balazs",
        "sequence": "additional",
        "affiliation": []
      },
      {
        "given": "A. John",
        "family": "Iafrate",
        "sequence": "additional",
        "affiliation": []
      }
    ],
    "member": "54368",
    "reference": [
      {
        "key": "2021111308000523000_2021.11.10.21265988v1.1",
        "doi-asserted-by": "crossref",
        "unstructured": "Addeo, A. , Shah, P.K. , Bordry, N. , Hudson, R.D. , Albracht, B. , Di Marco, M. , Kaklamani, V. , Dietrich, P.-Y. , Taylor, B.S. , Simand, P.-F. , et al. (2021). Immunogenicity of SARS-CoV-2 messenger RNA vaccines in patients with cancer. Cancer Cell.",
        "DOI": "10.1016/j.ccell.2021.06.009"
      },
      {
        "key": "2021111308000523000_2021.11.10.21265988v1.2",
        "doi-asserted-by": "crossref",
        "first-page": "e389",
        "DOI": "10.1016/S2352-3026(21)00110-1",
        "article-title": "Response to first vaccination against SARS-CoV-2 in patients with multiple myeloma",
        "volume": "8",
        "year": "2021",
        "journal-title": "Lancet Haematol"
      },
      {
        "key": "2021111308000523000_2021.11.10.21265988v1.3",
        "doi-asserted-by": "crossref",
        "unstructured": "Cho, A. , Muecksch, F. , Schaefer-Babajew, D. , Wang, Z. , Finkin, S. , Gaebler, C. , Ramos, V. , Cipolla, M. , Mendoza, P. , Agudelo, M. , et al. (2021). Anti-SARS-CoV-2 receptor binding domain antibody evolution after mRNA vaccination. Nature.",
        "DOI": "10.1101/2021.07.29.454333"
      },
      {
        "key": "2021111308000523000_2021.11.10.21265988v1.4",
        "doi-asserted-by": "publisher",
        "DOI": "10.1016/j.vaccine.2021.05.063"
      },
      {
        "key": "2021111308000523000_2021.11.10.21265988v1.5",
        "doi-asserted-by": "crossref",
        "unstructured": "Garcia-Beltran, W.F. , Lam, E.C. , Astudillo, M.G. , Schmidt, A.G. , Iafrate, A.J. , and Balazs Correspondence, A.B. (2021a). COVID-19-neutralizing antibodies predict disease severity and survival Graphical abstract Highlights d Severe COVID-19 associates with higher antibody production and neutralization titers d Neutralization potency of anti-RBD antibodies predicts disease severity and survival d Immunomodulatory COVID-19-directed therapies modulate antibody responses d COVID-19 sera neutralize D614 and G614 variants, but not pre-emergent WIV1-CoV.",
        "DOI": "10.1101/2020.10.15.20213512"
      },
      {
        "key": "2021111308000523000_2021.11.10.21265988v1.6",
        "doi-asserted-by": "publisher",
        "DOI": "10.1016/j.cell.2020.12.015"
      },
      {
        "key": "2021111308000523000_2021.11.10.21265988v1.7",
        "doi-asserted-by": "crossref",
        "first-page": "1297",
        "DOI": "10.1016/j.ccell.2021.09.001",
        "article-title": "Anti-spike antibody response to SARS-CoV-2 booster vaccination in patients with B cell-derived hematologic malignancies",
        "volume": "39",
        "year": "2021",
        "journal-title": "Cancer Cell"
      },
      {
        "key": "2021111308000523000_2021.11.10.21265988v1.8",
        "first-page": "2244",
        "article-title": "Risk prediction of covid-19 related death and hospital admission in adults after covid-19 vaccination: national prospective cohort study",
        "volume": "374",
        "year": "2021",
        "journal-title": "BMJ"
      },
      {
        "key": "2021111308000523000_2021.11.10.21265988v1.9",
        "doi-asserted-by": "crossref",
        "unstructured": "Iketani, S. , Liu, L. , Nair, M.S. , Mohri, H. , Wang, M. , Huang, Y. , and Ho, D.D. (2021). A third COVID-19 vaccine shot markedly boosts neutralizing antibody potency and breadth. MedRxiv 2021.08.11.21261670.",
        "DOI": "10.1101/2021.08.11.21261670"
      },
      {
        "key": "2021111308000523000_2021.11.10.21265988v1.10",
        "doi-asserted-by": "crossref",
        "unstructured": "Khoury, D.S. , Cromer, D. , Reynaldi, A. , Schlub, T.E. , Wheatley, A.K. , Juno, J.A. , Subbarao, K. , Kent, S.J. , Triccas, J.A. , and Davenport, M.P. (2021). Neutralizing antibody levels are highly predictive of immune protection from symptomatic SARS-CoV-2 infection. Nat. Med. 1\u20137.",
        "DOI": "10.1038/s41591-021-01377-8"
      },
      {
        "key": "2021111308000523000_2021.11.10.21265988v1.11",
        "doi-asserted-by": "publisher",
        "DOI": "10.1016/S0140-6736(20)31187-9"
      },
      {
        "key": "2021111308000523000_2021.11.10.21265988v1.12",
        "doi-asserted-by": "crossref",
        "unstructured": "Naranbhai, V. , Garcia-Beltran, W.F. , Chang, C.C. , Mairena, C.B. , Thierauf, J.C. , Kirkpatrick, G. , Onozato, M.L. , Cheng, J. , Denis, K.J. St. , Lam, E.C. , et al. (2021). Comparative immunogenicity and effectiveness of mRNA-1273, BNT162b2 and Ad26.COV2.S COVID-19 vaccines. MedRxiv 2021.07.18.21260732.",
        "DOI": "10.1101/2021.07.18.21260732"
      },
      {
        "key": "2021111308000523000_2021.11.10.21265988v1.13",
        "doi-asserted-by": "publisher",
        "DOI": "10.1038/s41598-021-82952-4"
      },
      {
        "key": "2021111308000523000_2021.11.10.21265988v1.14",
        "doi-asserted-by": "publisher",
        "DOI": "10.15585/mmwr.mm7038e1"
      },
      {
        "key": "2021111308000523000_2021.11.10.21265988v1.15",
        "doi-asserted-by": "crossref",
        "unstructured": "Tada, T. , Zhou, H. , Samanovic, M.I. , Dcosta, B.M. , Cornelius, A. , Mulligan, M.J. , and Landau, N.R. (2021). Comparison of Neutralizing Antibody Titers Elicited by mRNA and Adenoviral Vector Vaccine against SARS-CoV-2 Variants. BioRxiv 2021.07.19.452771.",
        "DOI": "10.1101/2021.07.19.452771"
      },
      {
        "key": "2021111308000523000_2021.11.10.21265988v1.16",
        "doi-asserted-by": "crossref",
        "unstructured": "Thakkar, A. , Gonzalez-Lugo, J.D. , Goradia, N. , Gali, R. , Shapiro, L.C. , Pradhan, K. , Rahman, S. , Kim, S.Y. , Ko, B. , Sica, R.A. , et al. (2021). Seroconversion rates following COVID-19 vaccination among patients with cancer. Cancer Cell.",
        "DOI": "10.1016/j.ccell.2021.06.002"
      },
      {
        "key": "2021111308000523000_2021.11.10.21265988v1.17",
        "doi-asserted-by": "publisher",
        "DOI": "10.1046/j.1365-2567.1999.00779.x"
      },
      {
        "key": "2021111308000523000_2021.11.10.21265988v1.18",
        "doi-asserted-by": "crossref",
        "first-page": "2372",
        "DOI": "10.1016/j.cell.2021.03.013",
        "article-title": "Article Multiple SARS-CoV-2 variants escape neutralization by vaccine-induced humoral immunity",
        "volume": "184",
        "year": "2021",
        "journal-title": "Cell"
      }
    ],
    "container-title": [],
    "original-title": [],
    "link": [
      {
        "URL": "https://syndication.highwire.org/content/doi/10.1101/2021.11.10.21265988",
        "content-type": "unspecified",
        "content-version": "vor",
        "intended-application": "similarity-checking"
      }
    ],
    "deposited": {
      "date-parts": [
        [
          2026,
          1,
          15
        ]
      ],
      "date-time": "2026-01-15T14:29:29Z",
      "timestamp": 1768487369000
    },
    "score": 1,
    "resource": {
      "primary": {
        "URL": "http://medrxiv.org/lookup/doi/10.1101/2021.11.10.21265988"
      }
    },
    "subtitle": [],
    "short-title": [],
    "issued": {
      "date-parts": [
        [
          2021,
          11,
          11
        ]
      ]
    },
    "references-count": 18,
    "URL": "https://doi.org/10.1101/2021.11.10.21265988",
    "relation": {
      "is-preprint-of": [
        {
          "id-type": "doi",
          "id": "10.1016/j.ccell.2021.12.002",
          "asserted-by": "subject"
        }
      ]
    },
    "subject": [],
    "published": {
      "date-parts": [
        [
          2021,
          11,
          11
        ]
      ]
    },
    "subtype": "preprint"
  }
}