{
  "status": "ok",
  "message-type": "work",
  "message-version": "1.0.0",
  "message": {
    "institution": [
      {
        "name": "medRxiv"
      }
    ],
    "indexed": {
      "date-parts": [
        [
          2026,
          2,
          27
        ]
      ],
      "date-time": "2026-02-27T01:36:40Z",
      "timestamp": 1772156200057,
      "version": "3.50.1"
    },
    "posted": {
      "date-parts": [
        [
          2020,
          7,
          19
        ]
      ]
    },
    "group-title": "Health Policy",
    "reference-count": 29,
    "publisher": "openRxiv",
    "content-domain": {
      "domain": [],
      "crossmark-restriction": false
    },
    "short-container-title": [],
    "accepted": {
      "date-parts": [
        [
          2020,
          7,
          19
        ]
      ]
    },
    "abstract": "<jats:title>ABSTRACT</jats:title>\n                <jats:p>We use an individual based model and national level epidemic simulations to estimate the medical costs of keeping the US economy open during COVID-19 pandemic under different counterfactual scenarios. We model an unmitigated scenario and 12 mitigation scenarios which differ in compliance behavior to social distancing strategies and to the duration of the stay-home order. Under each scenario we estimate the number of people who are likely to get infected and require medical attention, hospitalization, and ventilators. Given the per capita medical cost for each of these health states, we compute the total medical costs for each scenario and show the tradeoffs between deaths, costs, infections, compliance and the duration of stay-home order. We also consider the hospital bed capacity of each Hospital Referral Region (HRR) in the US to estimate the deficit in beds each HRR will likely encounter given the demand for hospital beds. We consider a case where HRRs share hospital beds among the neighboring HRRs during a surge in demand beyond the available beds and the impact it has in controlling additional deaths.</jats:p>",
    "DOI": "10.1101/2020.07.17.20156232",
    "type": "posted-content",
    "created": {
      "date-parts": [
        [
          2020,
          7,
          19
        ]
      ],
      "date-time": "2020-07-19T11:44:36Z",
      "timestamp": 1595159076000
    },
    "source": "Crossref",
    "is-referenced-by-count": 5,
    "title": [
      "Medical Costs of Keeping the US Economy Open During COVID-19"
    ],
    "prefix": "10.64898",
    "author": [
      {
        "given": "Jiangzhuo",
        "family": "Chen",
        "sequence": "first",
        "affiliation": []
      },
      {
        "given": "Anil",
        "family": "Vullikanti",
        "sequence": "additional",
        "affiliation": []
      },
      {
        "given": "Stefan",
        "family": "Hoops",
        "sequence": "additional",
        "affiliation": []
      },
      {
        "given": "Henning",
        "family": "Mortveit",
        "sequence": "additional",
        "affiliation": []
      },
      {
        "given": "Bryan",
        "family": "Lewis",
        "sequence": "additional",
        "affiliation": []
      },
      {
        "given": "Srinivasan",
        "family": "Venkatramanan",
        "sequence": "additional",
        "affiliation": []
      },
      {
        "given": "Wen",
        "family": "You",
        "sequence": "additional",
        "affiliation": []
      },
      {
        "given": "Stephen",
        "family": "Eubank",
        "sequence": "additional",
        "affiliation": []
      },
      {
        "given": "Madhav",
        "family": "Marathe",
        "sequence": "additional",
        "affiliation": []
      },
      {
        "given": "Chris",
        "family": "Barrett",
        "sequence": "additional",
        "affiliation": []
      },
      {
        "given": "Achla",
        "family": "Marathe",
        "sequence": "additional",
        "affiliation": []
      }
    ],
    "member": "54368",
    "reference": [
      {
        "key": "2021011423550764000_2020.07.17.20156232v1.1",
        "doi-asserted-by": "crossref",
        "unstructured": "Bartsch, S. M. et al. The potential health care costs and resource use associated with covid-19 in the united states. Heal. Aff. 10\u20131377 (2020).",
        "DOI": "10.1377/hlthaff.2020.00426"
      },
      {
        "key": "2021011423550764000_2020.07.17.20156232v1.2",
        "unstructured": "Rae, M. , Claxton, G. , Kurani, N. , McDermott, D. & Cox, C. Potential costs of coronavirus treatment for people with employer coverage. Peterson Cent. on Healthc. Kaiser Fam. Foundation 13 (2020). https://www.healthsystemtracker.org/brief/potential-costs-of-coronavirus-treatment-for-people-with-employer-coverage/."
      },
      {
        "key": "2021011423550764000_2020.07.17.20156232v1.3",
        "first-page": "1",
        "article-title": "Feedback between behavioral adaptations and disease dynamics",
        "volume": "8",
        "year": "2018",
        "journal-title": "Sci. reports"
      },
      {
        "key": "2021011423550764000_2020.07.17.20156232v1.4",
        "doi-asserted-by": "crossref",
        "first-page": "e1005521",
        "DOI": "10.1371/journal.pcbi.1005521",
        "article-title": "Epidemiological and economic impact of pandemic influenza in chicago: Priorities for vaccine interventions",
        "volume": "13",
        "year": "2017",
        "journal-title": "PLoS computational biology"
      },
      {
        "key": "2021011423550764000_2020.07.17.20156232v1.5",
        "doi-asserted-by": "crossref",
        "first-page": "180",
        "DOI": "10.1038/nature02541",
        "article-title": "Modelling disease outbreaks in realistic urban social networks",
        "volume": "429",
        "year": "2004",
        "journal-title": "Nat"
      },
      {
        "key": "2021011423550764000_2020.07.17.20156232v1.6",
        "unstructured": "Chen, J. et al. Network epidemiology for covid-19. SIAM News (2020)."
      },
      {
        "key": "2021011423550764000_2020.07.17.20156232v1.7",
        "unstructured": "Adiga, A. , Venkatramanan, S. , Schlitt, J. & et al. Evaluating the impact of international airline suspensions on the early global spread of covid-19. Tech. Rep., medRxiv (2020). https://www.medrxiv.org/content/10.1101/2020.02.20.20025882v2.full.pdf."
      },
      {
        "key": "2021011423550764000_2020.07.17.20156232v1.8",
        "unstructured": "Machi, D. et al. Scalable epidemiological workflows to support covid-19 planning and response. Tech. Rep. SC-TR-2020, Network Systems Science and Advanced Computing Division, BII, University of Virginia (2020). https://www.dropbox.com/s/2uk2wnbte95mk5y/main.v87.7020f2c.pdf?dl=0."
      },
      {
        "key": "2021011423550764000_2020.07.17.20156232v1.9",
        "doi-asserted-by": "crossref",
        "first-page": "221",
        "DOI": "10.1186/s12879-019-3703-2",
        "article-title": "Impact of demographic disparities in social distancing and vaccination on influenza epidemics in urban and rural regions of the united states",
        "volume": "19",
        "year": "2019",
        "journal-title": "BMC infectious diseases"
      },
      {
        "key": "2021011423550764000_2020.07.17.20156232v1.10",
        "first-page": "415",
        "article-title": "Creating synthetic baseline populations",
        "volume": "30",
        "year": "1996",
        "journal-title": "Transp. Res. Part A: Policy Pract"
      },
      {
        "key": "2021011423550764000_2020.07.17.20156232v1.11",
        "doi-asserted-by": "crossref",
        "unstructured": "Barrett, C. et al. Generation and analysis of large synthetic social contact networks. In Winter Simulation Conference, 1003\u20131014 (Winter Simulation Conference, 2009).",
        "DOI": "10.1109/WSC.2009.5429425"
      },
      {
        "key": "2021011423550764000_2020.07.17.20156232v1.12",
        "doi-asserted-by": "crossref",
        "unstructured": "Halloran, M. E. et al. Modeling targeted layered containment of an influenza pandemic in the United States. In Proceedings of the National Academy of Sciences (PNAS), 4639\u20134644 (2008). PMCID:PMC2290797.",
        "DOI": "10.1073/pnas.0706849105"
      },
      {
        "key": "2021011423550764000_2020.07.17.20156232v1.13",
        "unstructured": "Barrett, C. , Eubank, S. & Marathe, M. An interaction-based approach to computational epidemiology. In AAAI, 1590\u20131593 (2008)."
      },
      {
        "key": "2021011423550764000_2020.07.17.20156232v1.14",
        "doi-asserted-by": "crossref",
        "first-page": "446",
        "DOI": "10.1080/17513751003778687",
        "article-title": "Detail in network models of epidemiology: Are we there yet?",
        "volume": "4",
        "year": "2010",
        "journal-title": "J. Biol. Dyn"
      },
      {
        "key": "2021011423550764000_2020.07.17.20156232v1.15",
        "doi-asserted-by": "crossref",
        "first-page": "e25149",
        "DOI": "10.1371/journal.pone.0025149",
        "article-title": "Comparing effectiveness of top-down and bottom-up strategies in containing influenza",
        "volume": "6",
        "year": "2011",
        "journal-title": "PLoS ONE"
      },
      {
        "key": "2021011423550764000_2020.07.17.20156232v1.16",
        "doi-asserted-by": "crossref",
        "unstructured": "Rivers, C. , Lofgren, E. , Marathe, M. , Eubank, S. & Lewis, B. Modeling the impact of interventions on an epidemic of Ebola in Sierra Leone and Liberia. PLoS Curr. (2014). PMCID: PMC4399521.",
        "DOI": "10.1371/currents.outbreaks.4d41fe5d6c05e9df30ddce33c66d084c"
      },
      {
        "key": "2021011423550764000_2020.07.17.20156232v1.17",
        "unstructured": "Bisset, K. & Marathe, M. A cyber-environment to support pandemic planning and response. DOE SciDAC Mag. 36\u201347 (2009)."
      },
      {
        "key": "2021011423550764000_2020.07.17.20156232v1.18",
        "unstructured": "Centers for Disease Control and Prevention. Covid-19 pandemic planning scenarios. https://www.cdc.gov/coronavirus/2019-ncov/hcp/planning-scenarios-h.pdf. (2020). [Online, accessed July 8, 2020]."
      },
      {
        "key": "2021011423550764000_2020.07.17.20156232v1.19",
        "unstructured": "Virginia Department of Health. Uva covid-19 model: Weekly update. https://www.vdh.virginia.gov/coronavirus/2020/05/19/uva-covid-19-model-weekly-update/ (2020). [Online, accessed July 8, 2020]."
      },
      {
        "key": "2021011423550764000_2020.07.17.20156232v1.20",
        "unstructured": "Merrill, D. No one values your life more than the federal government. Bloom. https://www.bloomberg.com/graphics/2017-value-of-life (2017)."
      },
      {
        "key": "2021011423550764000_2020.07.17.20156232v1.21",
        "doi-asserted-by": "crossref",
        "unstructured": "Alvarez, F. E. , Argente, D. & Lippi, F. A simple planning problem for covid-19 lockdown. Tech. Rep., National Bureau of Economic Research (2020).",
        "DOI": "10.3386/w26981"
      },
      {
        "key": "2021011423550764000_2020.07.17.20156232v1.22",
        "doi-asserted-by": "crossref",
        "first-page": "83",
        "DOI": "10.1002/hec.911",
        "article-title": "Valuation of the risk of sars in taiwan",
        "volume": "14",
        "year": "2005",
        "journal-title": "Heal. Econ"
      },
      {
        "key": "2021011423550764000_2020.07.17.20156232v1.23",
        "doi-asserted-by": "crossref",
        "first-page": "253",
        "DOI": "10.1002/pam.10026",
        "article-title": "What determines the value of life? a meta-analysis",
        "volume": "21",
        "year": "2002",
        "journal-title": "J. Policy analysis Manag"
      },
      {
        "key": "2021011423550764000_2020.07.17.20156232v1.24",
        "unstructured": "Education Week. Map: Coronavirus and school closures. https://www.edweek.org/ew/section/multimedia/map-coronavirus-and-school-closures.html (2020). [Online, accessed June 30, 2020]."
      },
      {
        "key": "2021011423550764000_2020.07.17.20156232v1.25",
        "unstructured": "Wikipedia contributors. U.S. state and local government response to the covid-19 pandemic. https://en.wikipedia.org/wiki/U.S._state_and_local_government_response_to_the_COVID-19_pandemic (2020). [Online, accessed June 30, 2020]."
      },
      {
        "key": "2021011423550764000_2020.07.17.20156232v1.26",
        "unstructured": "US News. Gov. andrew cuomo orders hospitals to increase capacity by 50%. https://www.usnews.com/news/health-news/articles/2020-03-23/new-york-gov-andrew-cuomo-orders-hospitals-to-increase-capacity-by-50 (2020). [Online, accessed July 8, 2020]."
      },
      {
        "key": "2021011423550764000_2020.07.17.20156232v1.27",
        "doi-asserted-by": "publisher",
        "DOI": "10.1073/pnas.2004064117"
      },
      {
        "key": "2021011423550764000_2020.07.17.20156232v1.28",
        "doi-asserted-by": "publisher",
        "DOI": "10.2307/1268522"
      },
      {
        "key": "2021011423550764000_2020.07.17.20156232v1.29",
        "doi-asserted-by": "crossref",
        "first-page": "174",
        "DOI": "10.1080/00224065.1981.11978748",
        "article-title": "An approach to sensitivity analysis of computer models: Part i\u2014introduction, input variable selection and preliminary variable assessment",
        "volume": "13",
        "year": "1981",
        "journal-title": "J. quality technology"
      }
    ],
    "container-title": [],
    "original-title": [],
    "link": [
      {
        "URL": "https://syndication.highwire.org/content/doi/10.1101/2020.07.17.20156232",
        "content-type": "unspecified",
        "content-version": "vor",
        "intended-application": "similarity-checking"
      }
    ],
    "deposited": {
      "date-parts": [
        [
          2026,
          1,
          15
        ]
      ],
      "date-time": "2026-01-15T13:48:42Z",
      "timestamp": 1768484922000
    },
    "score": 1,
    "resource": {
      "primary": {
        "URL": "http://medrxiv.org/lookup/doi/10.1101/2020.07.17.20156232"
      }
    },
    "subtitle": [],
    "short-title": [],
    "issued": {
      "date-parts": [
        [
          2020,
          7,
          19
        ]
      ]
    },
    "references-count": 29,
    "URL": "https://doi.org/10.1101/2020.07.17.20156232",
    "relation": {
      "is-preprint-of": [
        {
          "id-type": "doi",
          "id": "10.1038/s41598-020-75280-6",
          "asserted-by": "subject"
        }
      ],
      "has-review": [
        {
          "id-type": "doi",
          "id": "10.1162/2e3983f5.8b63288a",
          "asserted-by": "object"
        },
        {
          "id-type": "doi",
          "id": "10.1162/2e3983f5.f7964612",
          "asserted-by": "object"
        },
        {
          "id-type": "doi",
          "id": "10.1162/2e3983f5.f72ebe6a",
          "asserted-by": "object"
        }
      ]
    },
    "subject": [],
    "published": {
      "date-parts": [
        [
          2020,
          7,
          19
        ]
      ]
    },
    "subtype": "preprint"
  }
}